leblad/__init__.py
leblad/indexapi.py
leblad/utils.py
leblad-0.0.4.dist-info/LICENSE
leblad-0.0.4.dist-info/METADATA
leblad-0.0.4.dist-info/WHEEL
leblad-0.0.4.dist-info/top_level.txt
leblad-0.0.4.dist-info/RECORD
