Metadata-Version: 2.1
Name: leblad
Version: 0.0.4
Summary: the python version of leblad library,  provide a list of Algerian administrative areas with many useful APIsbased on  dzcode-io/leblad
Home-page: https://github.com/abderrahmaneMustapha/leblad-py
Author: Toumi abderrahmane
Author-email: abderrahmanemustapha030898@gmail.com
License: UNKNOWN
Platform: UNKNOWN
Classifier: Programming Language :: Python :: 3
Classifier: License :: OSI Approved :: MIT License
Classifier: Operating System :: OS Independent
Requires-Python: >=3.6
